top.sv
module top(input logic clk, reset_n,
			output logic [3:0] led);
	
	parameter MAX_CYCLE_WIDTH = 32;
   
	logic [MAX_CYCLE_WIDTH-1:0] current_cycle;

	simulator #(MAX_CYCLE_WIDTH) simulator(clk, reset_n, led[1:0], current_cycle);
	assign led[3:2] = 2'b0;
			
endmodule

module simulator  #(parameter MAX_CYCLE_WIDTH = 32)
			(input logic clk, reset_n,
			output logic [1:0] state,
			output logic [MAX_CYCLE_WIDTH-1:0] current_cycle);
	
	parameter MAX_CYCLE = {MAX_CYCLE_WIDTH{1'b1}};
	
	logic [1:0] next_state;
	
	always_ff @(posedge clk or negedge reset_n)
		if (!reset_n) begin
			state <= 2'b00;
			current_cycle <= {MAX_CYCLE_WIDTH{1'b0}};
		end
		else begin
			state <= next_state;
			
			if(current_cycle < MAX_CYCLE)		
				current_cycle <= current_cycle + 1;
		end
	
	always_comb
		case (state)
			2'b00: //INVALID
				next_state <= 2'b01;
			2'b01: //INITIALIZED
				next_state <= 2'b10;
			2'b10: begin //RUNNING
				next_state <= 2'b10;
				
				if (current_cycle == MAX_CYCLE)
					next_state <= 2'b11;
			end
			2'b11://COMPLETED
				next_state <= 2'b11;
			default:
				next_state <= 2'bx;
		endcase
	
endmodule

testbench.sv
`timescale 1ps/1ps

module testbench();
	
	parameter MAX_CYCLE_WIDTH = 5;

	logic clk;
	logic reset_n;
	  
	logic [1:0] state;
	logic [MAX_CYCLE_WIDTH-1:0] current_cycle;

	// instantiate device to be tested  
	simulator #(MAX_CYCLE_WIDTH) dut(clk, reset_n, state, current_cycle);

	// generate clock to sequence tests
	always #10 clk <= ! clk;
	  
	// initialize test
	initial #0 begin
		clk = 0;		
		reset_n = 0;
		#10;		
		reset_n = 1;
	end

	// check results
	always @(negedge clk)
		$display("state = %2b", state);

endmodule

test.vcd
$date
	Mon Feb  1 21:52:26 2016
$end
$version
	Icarus Verilog
$end
$timescale
	1ps
$end
$scope module testbench $end
$scope module dut $end
$var wire 1 ! clk $end
$var wire 1 " reset_n $end
$var reg 5 # current_cycle [4:0] $end
$var reg 2 $ next_state [1:0] $end
$var reg 2 % state [1:0] $end
$upscope $end
$upscope $end
$enddefinitions $end
#0
$dumpvars
b0 %
b1 $
b0 #
0"
0!
$end
#10
b10 $
b1 #
b1 %
1!
1"
#20
0!
#30
b10 #
b10 %
1!
#40
0!
#50
b11 #
1!
#60
0!
#70
b100 #
1!
#80
0!
#90
b101 #
1!
#100
0!
#110
b110 #
1!
#120
0!
#130
b111 #
1!
#140
0!
#150
b1000 #
1!
#160
0!
#170
b1001 #
1!
#180
0!
#190
b1010 #
1!
#200
0!
#210
b1011 #
1!
#220
0!
#230
b1100 #
1!
#240
0!
#250
b1101 #
1!
#260
0!
#270
b1110 #
1!
#280
0!
#290
b1111 #
1!
#300
0!
#310
b10000 #
1!
#320
0!
#330
b10001 #
1!
#340
0!
#350
b10010 #
1!
#360
0!
#370
b10011 #
1!
#380
0!
#390
b10100 #
1!
#400
0!
#410
b10101 #
1!
#420
0!
#430
b10110 #
1!
#440
0!
#450
b10111 #
1!
#460
0!
#470
b11000 #
1!
#480
0!
#490
b11001 #
1!
#500
0!
#510
b11010 #
1!
#520
0!
#530
b11011 #
1!
#540
0!
#550
b11100 #
1!
#560
0!
#570
b11101 #
1!
#580
0!
#590
b11110 #
1!
#600
0!
#610
b11 $
b11111 #
1!
#620
0!
#630
b11 %
1!
